{"lastBuildDate":"Mon, 22 Jun 2020 04:59:50 +0900","total":348,"start":1,"display":10,"items":[{"title":"내가 사랑했던 모든 남자들에게: P.S. 여전히 널 사랑해","link":"https://movie.naver.com/movie/bi/mi/basic.nhn?code=191641","image":"https://ssl.pstatic.net/imgmovie/mdi/mit110/1916/191641_P01_142502.jpg","subtitle":"To All the Boys: P.S. I Still Love You","pubDate":"2020","director":"마이클 피모그나리|","actor":"라나 콘도르|노아 센티네오|","userRating":"0.00"},{"title":"우리가 꽃들이라면","link":"https://movie.naver.com/movie/bi/mi/basic.nhn?code=194068","image":"https://ssl.pstatic.net/imgmovie/mdi/mit110/1940/194068_P01_142133.png","subtitle":"We Bloom","pubDate":"2020","director":"김율희|","actor":"","userRating":"0.00"},{"title":"바다가 없는 마을","link":"https://movie.naver.com/movie/bi/mi/basic.nhn?code=194075","image":"https://ssl.pstatic.net/imgmovie/mdi/mit110/1940/194075_P01_110450.jpg","subtitle":"Town without Sea","pubDate":"2020","director":"이케다 에라이자|","actor":"","userRating":"0.00"},{"title":"그해 우리가 발견한 것","link":"https://movie.naver.com/movie/bi/mi/basic.nhn?code=191331","image":"https://ssl.pstatic.net/imgmovie/mdi/mit110/1913/191331_P02_181214.jpg","subtitle":"The Year of the Discovery","pubDate":"2020","director":"루이스 로페즈 카라스코|","actor":"","userRating":"0.00"},{"title":"어제 일은 모두 괜찮아","link":"https://movie.naver.com/movie/bi/mi/basic.nhn?code=173842","image":"https://ssl.pstatic.net/imgmovie/mdi/mit110/1738/173842_P12_112840.jpg","subtitle":"The Fault Is Not Yours.","pubDate":"2019","director":"이성한|","actor":"김재철|윤찬영|손상연|김민주|김진영|","userRating":"8.76"},{"title":"음란주택:노예가 된 아내","link":"https://movie.naver.com/movie/bi/mi/basic.nhn?code=191666","image":"https://ssl.pstatic.net/imgmovie/mdi/mit110/1916/191666_P01_160650.jpg","subtitle":"","pubDate":"2019","director":"한동호|","actor":"새봄|민도윤|김민정|","userRating":"10.00"},{"title":"나는 네가 될 수 없다","link":"https://movie.naver.com/movie/bi/mi/basic.nhn?code=190202","image":"https://ssl.pstatic.net/imgmovie/mdi/mit110/1902/190202_P01_174020.jpg","subtitle":"","pubDate":"2019","director":"최원근|","actor":"금아연|","userRating":"0.00"},{"title":"운동선수 - 내가 그에게 빠진 나날","link":"https://movie.naver.com/movie/bi/mi/basic.nhn?code=189912","image":"https://ssl.pstatic.net/imgmovie/mdi/mit110/1899/189912_P01_170059.jpg","subtitle":"Athlete: Ore ga kare ni oboreta hibi","pubDate":"2019","director":"오에 타카마사|","actor":"","userRating":"0.00"},{"title":"내 여자가 된 선생님","link":"https://movie.naver.com/movie/bi/mi/basic.nhn?code=194781","image":"https://ssl.pstatic.net/imgmovie/mdi/mit110/1947/194781_P01_173820.jpg","subtitle":"Trained tutor","pubDate":"2019","director":"아이바 켄타|","actor":"","userRating":"0.00"},{"title":"남편 상사의 노예가 된 아내","link":"https://movie.naver.com/movie/bi/mi/basic.nhn?code=189064","image":"https://ssl.pstatic.net/imgmovie/mdi/mit110/1890/189064_P01_173837.jpg","subtitle":"Greedy boss","pubDate":"2019","director":"호쿠시 겐지|","actor":"","userRating":"0.00"}]}